{"message":"Erro em: /users/123123 com os parâmetros {\"path\":\"/users/123123\",\"query\":{},\"payload\":null,\"params\":{\"id\":\"123123\"},\"host\":\"localhost:8081\",\"username\":\"\",\"at\":\"2018-11-11T18:11:06.794Z\",\"err\":{\"message\":\"Cast to ObjectId failed for value \\\"123123\\\" at path \\\"_id\\\" for model \\\"Users\\\"\",\"name\":\"CastError\",\"stringValue\":\"\\\"123123\\\"\",\"kind\":\"ObjectId\",\"value\":\"123123\",\"path\":\"_id\"}}","level":"error"}
{"message":"Erro em: /users com os parâmetros {\"path\":\"/users\",\"query\":{},\"payload\":{\"name\":\"Projeto número\",\"email\":\"testv@testv.com\",\"area\":\"teste\",\"photo\":\"/img/LiPBOJLyqOBan9EUiGTt.png\",\"phone\":\"000\",\"cpf\":\"123\",\"gender\":\"m\",\"birthDate\":\"1997-01-31T00:00:00.000Z\"},\"params\":{},\"host\":\"localhost:8081\",\"username\":\"\",\"at\":\"2018-11-11T22:24:55.060Z\",\"err\":{\"errors\":{\"password\":{\"message\":\"Path `password` is required.\",\"name\":\"ValidatorError\",\"properties\":{\"message\":\"Path `password` is required.\",\"type\":\"required\",\"path\":\"password\"},\"kind\":\"required\",\"path\":\"password\"}},\"_message\":\"Users validation failed\",\"message\":\"Users validation failed: password: Path `password` is required.\",\"name\":\"ValidationError\"}}","level":"error"}
{"message":"Erro em: /users com os parâmetros {\"path\":\"/users\",\"query\":{},\"payload\":{\"name\":\"Projeto número\",\"email\":\"testv@testv.com\",\"area\":\"teste\",\"photo\":\"/img/Dcb8y4wGbl8Pj4zT0a4y.png\",\"phone\":\"000\",\"cpf\":\"123\",\"gender\":\"m\",\"birthDate\":\"1997-01-31T00:00:00.000Z\"},\"params\":{},\"host\":\"localhost:8081\",\"username\":\"\",\"at\":\"2018-11-11T22:25:21.997Z\",\"err\":{\"errors\":{\"password\":{\"message\":\"Path `password` is required.\",\"name\":\"ValidatorError\",\"properties\":{\"message\":\"Path `password` is required.\",\"type\":\"required\",\"path\":\"password\"},\"kind\":\"required\",\"path\":\"password\"}},\"_message\":\"Users validation failed\",\"message\":\"Users validation failed: password: Path `password` is required.\",\"name\":\"ValidationError\"}}","level":"error"}
{"message":"Erro em: /users com os parâmetros {\"path\":\"/users\",\"query\":{},\"payload\":{\"name\":\"Projeto número\",\"email\":\"testv@testv.com\",\"area\":\"teste\",\"photo\":\"/img/XAAVBY1Jd3JTiISa1frn.png\",\"phone\":\"000\",\"cpf\":\"123\",\"gender\":\"m\",\"birthDate\":\"1997-01-31T00:00:00.000Z\"},\"params\":{},\"host\":\"localhost:8081\",\"username\":\"\",\"at\":\"2018-11-11T22:25:44.416Z\",\"err\":{\"errors\":{\"password\":{\"message\":\"Path `password` is required.\",\"name\":\"ValidatorError\",\"properties\":{\"message\":\"Path `password` is required.\",\"type\":\"required\",\"path\":\"password\"},\"kind\":\"required\",\"path\":\"password\"}},\"_message\":\"Users validation failed\",\"message\":\"Users validation failed: password: Path `password` is required.\",\"name\":\"ValidationError\"}}","level":"error"}
{"message":"Erro em: /users com os parâmetros {\"path\":\"/users\",\"query\":{},\"payload\":{\"name\":\"Projeto número\",\"email\":\"testv@testv.com\",\"area\":\"teste\",\"password\":\"$2b$10$5d5rabPpHysFLZ20Ry2oUeOFKZvvEkSRNYIWSQR5MJY.jO54P6qSu\",\"photo\":\"/img/jFH4VzP71Lkr8Mhtr2kW.png\",\"phone\":\"000\",\"cpf\":\"123\",\"gender\":\"m\",\"birthDate\":\"1997-01-31T00:00:00.000Z\"},\"params\":{},\"host\":\"localhost:8081\",\"username\":\"\",\"at\":\"2018-11-11T22:27:33.106Z\",\"err\":{\"driver\":true,\"name\":\"MongoError\",\"index\":0,\"code\":11000,\"errmsg\":\"E11000 duplicate key error collection: hapijsmongo.users index: email_1 dup key: { : \\\"testv@testv.com\\\" }\"}}","level":"error"}
{"message":"Erro em: /users com os parâmetros {\"path\":\"/users\",\"query\":{},\"payload\":{\"name\":\"Projeto número\",\"email\":\"testv1@testv.com\",\"area\":\"teste\",\"password\":\"$2b$10$Gu0TeAu8i3UgAlOySIvEFuonfelimF5vQQ3w5vRHNB5g5IgexP.mm\",\"photo\":\"/img/ahprkD3XqU6fV2o8mHL2.png\",\"phone\":\"000\",\"cpf\":\"123\",\"gender\":\"m\",\"birthDate\":\"1997-01-31T00:00:00.000Z\",\"createdAt\":\"2018-11-11T22:27:35.401Z\"},\"params\":{},\"host\":\"localhost:8081\",\"username\":\"\",\"at\":\"2018-11-11T22:28:42.891Z\",\"err\":{\"driver\":true,\"name\":\"MongoError\",\"index\":0,\"code\":11000,\"errmsg\":\"E11000 duplicate key error collection: hapijsmongo.users index: email_1 dup key: { : \\\"testv1@testv.com\\\" }\"}}","level":"error"}
{"message":"Erro em: /users com os parâmetros {\"path\":\"/users\",\"query\":{},\"payload\":{\"name\":\"Projeto número\",\"email\":\"testv1@testv.com\",\"area\":\"teste\",\"password\":\"$2b$10$hRpq/7wikVJ.QjadouTTp.qIYiBh4HS.PDJXX6fdIJr1/xTtsJSWq\",\"photo\":\"/img/VFMuPZ6BBVRQMVaV2rPI.png\",\"phone\":\"000\",\"cpf\":\"123\",\"gender\":\"m\",\"birthDate\":\"1997-01-31T00:00:00.000Z\",\"createdAt\":\"2018-11-11T22:27:35.401Z\"},\"params\":{},\"host\":\"localhost:8081\",\"username\":\"\",\"at\":\"2018-11-11T22:29:00.393Z\",\"err\":{\"driver\":true,\"name\":\"MongoError\",\"index\":0,\"code\":11000,\"errmsg\":\"E11000 duplicate key error collection: hapijsmongo.users index: email_1 dup key: { : \\\"testv1@testv.com\\\" }\"}}","level":"error"}
{"message":"Erro em: /users com os parâmetros {\"path\":\"/users\",\"query\":{},\"payload\":{\"name\":\"Projeto número\",\"email\":\"testv1@testv.com\",\"area\":\"teste\",\"password\":\"$2b$10$.rzdWxeViOZkbYGwYSbvxO49ZvmWDfNSRqKaY2vk9xfK4swkWm1bi\",\"photo\":\"/img/ArwrO1rVQeQv7fscEabk.png\",\"phone\":\"000\",\"cpf\":\"123\",\"gender\":\"m\",\"birthDate\":\"1997-01-31T00:00:00.000Z\",\"createdAt\":\"2018-11-11T00:00:00.000Z\"},\"params\":{},\"host\":\"localhost:8081\",\"username\":\"\",\"at\":\"2018-11-11T22:30:21.937Z\",\"err\":{\"driver\":true,\"name\":\"MongoError\",\"index\":0,\"code\":11000,\"errmsg\":\"E11000 duplicate key error collection: hapijsmongo.users index: email_1 dup key: { : \\\"testv1@testv.com\\\" }\"}}","level":"error"}
